order_status_notify/__init__.py
order_status_notify/email_utils.py
order_status_notify-0.2.3.dist-info/METADATA
order_status_notify-0.2.3.dist-info/WHEEL
order_status_notify-0.2.3.dist-info/top_level.txt
order_status_notify-0.2.3.dist-info/RECORD
