Metadata-Version: 2.4
Name: order_status_notify
Version: 0.2.3
Summary: A lightweight Django utility for sending email notifications on order status updates.
Home-page: https://pypi.org/project/order-status-notify/
Author: Hetik
Author-email: hetikchandaria66@gmail.com
Classifier: Programming Language :: Python :: 3
Classifier: Framework :: Django
Classifier: Framework :: Django :: 3.2
Classifier: Operating System :: OS Independent
Requires-Python: >=3.8
Requires-Dist: Django<4.0,>=3.2
Dynamic: author
Dynamic: author-email
Dynamic: classifier
Dynamic: description
Dynamic: description-content-type
Dynamic: home-page
Dynamic: requires-dist
Dynamic: requires-python
Dynamic: summary
